disco_sound/__init__.py
disco_sound/__main__.py
disco_sound/infer.py
disco_sound/label.py
disco_sound/visualize.py
disco_sound/callbacks/__init__.py
disco_sound/cfg/__init__.py
disco_sound/cfg/extract_config.py
disco_sound/cfg/infer_config.py
disco_sound/cfg/label_config.py
disco_sound/cfg/shuffle_config.py
disco_sound/cfg/train_config.py
disco_sound/cfg/viz_config.py
disco_sound/datasets/__init__.py
disco_sound/datasets/beetles_data.py
disco_sound/datasets/twoD_dataset.py
disco_sound/datasets/whale_data.py
disco_sound/models/__init__.py
disco_sound/models/unet_1d.py
disco_sound/models/unet_2d.py
disco_sound/resources/birds.wav
disco_sound/resources/example.csv
disco_sound/resources/example.wav
disco_sound/resources/example_beetles_config.yaml
disco_sound/resources/example_inference_image.png
disco_sound/resources/example_labels.csv
disco_sound/resources/hello.pkl
disco_sound/resources/western_meadowlark.wav
disco_sound/resources/noised_iqr/snr_0_ensemble_10_random_init/ground_truth.pkl
disco_sound/resources/noised_iqr/snr_0_ensemble_10_random_init/hmm_predictions.pkl
disco_sound/resources/noised_iqr/snr_0_ensemble_10_random_init/iqrs.pkl
disco_sound/resources/noised_iqr/snr_0_ensemble_10_random_init/median_predictions.pkl
disco_sound/resources/noised_iqr/snr_0_ensemble_10_random_init/votes.pkl
disco_sound/resources/noised_iqr/snr_10_ensemble_10_random_init/ground_truth.pkl
disco_sound/resources/noised_iqr/snr_10_ensemble_10_random_init/hmm_predictions.pkl
disco_sound/resources/noised_iqr/snr_10_ensemble_10_random_init/iqrs.pkl
disco_sound/resources/noised_iqr/snr_10_ensemble_10_random_init/median_predictions.pkl
disco_sound/resources/noised_iqr/snr_10_ensemble_10_random_init/votes.pkl
disco_sound/resources/noised_iqr/snr_15_ensemble_10_random_init/ground_truth.pkl
disco_sound/resources/noised_iqr/snr_15_ensemble_10_random_init/hmm_predictions.pkl
disco_sound/resources/noised_iqr/snr_15_ensemble_10_random_init/iqrs.pkl
disco_sound-0.0.2.dist-info/entry_points.txt
disco_sound-0.0.2.dist-info/LICENSE.txt
disco_sound-0.0.2.dist-info/WHEEL
disco_sound-0.0.2.dist-info/METADATA
disco_sound-0.0.2.dist-info/RECORD
