Metadata-Version: 2.1
Name: disco_sound
Version: 0.0.2
Summary: DISCO Implements Sound Classification Obediently.
Author-email: Kayla Irish <kayla.irish@umontana.edu>, Thomas Colligan <thomas.colligan@umontana.edu>
Requires-Dist: numpy
Requires-Dist: matplotlib
Requires-Dist: pytorch_lightning
Requires-Dist: torchaudio
Requires-Dist: pomegranate
Requires-Dist: pyyaml
Requires-Dist: numpy<1.24.0
Requires-Dist: tensorboard
Requires-Dist: sacred
Requires-Dist: pandas
Requires-Dist: tqdm
Requires-Dist: scikit-learn
Project-URL: Home, https://github.com/TravisWheelerLab/disco
